[
	{
		"Name": "Pomodoro Melanzane di Pollo Tomatensoße mit Aubergine und Hähnchen (Sw), Reis",
		"Category": "Pastabar",
		"Date": "2025-02-06",
		"Additives": {
			"Sw": "Schwefeldioxid und Sulfite (Konzentration über 10mg/kg oder 10mg/l)"
		},
		"PriceAttendant": 1.1,
		"PriceGuest": 1.3,
		"PriceStudent": 0.85,
		"LactoseFree": true,
		"Poultry": true
	},
	{
		"Name": "Tortellini mit Käsefüllung (Mi,GlW), Noci di zucchine mit Zucchini-Walnusssoße (Mi,GlW,GlG,NWa)",
		"Category": "Pastabar",
		"Date": "2025-02-06",
		"Additives": {
			"GlG": "glutenhaltiges Getreide und daraus hergestellte Erzeugnisse (Gerste)",
			"GlW": "glutenhaltiges Getreide und daraus hergestellte Erzeugnisse (Weizen)",
			"Mi": "Milch und Milcherzeugnisse (einschließlich Laktose)",
			"NWa": "Schalenfrüchte (Walnüsse)/-erzeugnisse"
		},
		"PriceAttendant": 1.1,
		"PriceGuest": 1.3,
		"PriceStudent": 0.85,
		"Vegetarian": true
	},
	{
		"Name": "Erbsensuppe mit Räuchertofu (So,Sl,GlW)",
		"Category": "Pottkieker",
		"Date": "2025-02-06",
		"Additives": {
			"GlW": "glutenhaltiges Getreide und daraus hergestellte Erzeugnisse (Weizen)",
			"Sl": "Sellerie und Sellerieerzeugnisse",
			"So": "Soja und Sojaerzeugnisse"
		},
		"PriceAttendant": 3.5,
		"PriceGuest": 4.7,
		"PriceStudent": 2.2,
		"LactoseFree": true,
		"Vegan": true
	},
	{
		"Name": "Bolognese mit Rindfleisch (Sl)",
		"Category": "CampusKlassiker",
		"Date": "2025-02-06",
		"Additives": {
			"GlW": "glutenhaltiges Getreide und daraus hergestellte Erzeugnisse (Weizen)",
			"Mi": "Milch und Milcherzeugnisse (einschließlich Laktose)",
			"Sl": "Sellerie und Sellerieerzeugnisse"
		},
		"PriceAttendant": 4.8,
		"PriceGuest": 6.0,
		"PriceStudent": 3.5,
		"Beef": true
	},
	{
		"Name": "Bratnudeln mit Gemüsestreifen (2,Ei,So,Se,GlW), Mini Frühlingsrollen (So,GlW), scharfer Asia-Dip",
		"Category": "CampusSpezial",
		"Date": "2025-02-06",
		"Additives": {
			"2": "Konservierungsstoff",
			"Ei": "Ei und Eierzeugnisse",
			"GlW": "glutenhaltiges Getreide und daraus hergestellte Erzeugnisse (Weizen)",
			"Se": "Sesamsamen und Sesamsamenerzeugnisse",
			"So": "Soja und Sojaerzeugnisse"
		},
		"PriceAttendant": 4.95,
		"PriceGuest": 6.15,
		"PriceStudent": 3.65,
		"LactoseFree": true,
		"Vegetarian": true
	},
	{
		"Name": "Schupfnudeln mit Champignons, Spitzkohl und marinierten Tofuscheiben (1,2,So,Sf,Sw,GlW)",
		"Category": "CampusVital",
		"Date": "2025-02-06",
		"Additives": {
			"1": "Farbstoff",
			"2": "Konservierungsstoff",
			"GlW": "glutenhaltiges Getreide und daraus hergestellte Erzeugnisse (Weizen)",
			"Sf": "Senf und Senferzeugnisse",
			"So": "Soja und Sojaerzeugnisse",
			"Sw": "Schwefeldioxid und Sulfite (Konzentration über 10mg/kg oder 10mg/l)"
		},
		"PriceAttendant": 6.55,
		"PriceGuest": 7.75,
		"PriceStudent": 5.25,
		"LactoseFree": true,
		"Vegan": true
	}
]
