[
	{
		"Name": "Pikanter Bulgursalat mit Mangold und Rosinen (Gl), gebratene Hähnchenstreifen (Se), Sourcreme (4, Ei, La, Sf)",
		"Category": "Tagesgericht",
		"Date": "2020-07-14",
		"Additives": {
			"4": "Geschmacksverstärker",
			"Ei": "Ei/-erzeugnisse",
			"Gl": "Glutenhaltiges Getreide und daraus hergestellte Erzeugnissse",
			"La": "Milch/-erzeugnisse (einschl. Laktose)",
			"Se": "Sesam/-erzeugnisse",
			"Sf": "Senf/-erzeugnisse"
		},
		"PriceAttendant": 3.45,
		"PriceGuest": 3.9,
		"PriceStudent": 3.0,
		"Poultry": true
	},
	{
		"Name": "Pikanter Bulgursalat mit Mangold und Rosinen (Gl), Mariniertes Tofusteak (2, Gl, So)",
		"Category": "Vegetarisch",
		"Date": "2020-07-14",
		"Additives": {
			"2": "Konservierungsstoffe",
			"Gl": "Glutenhaltiges Getreide und daraus hergestellte Erzeugnissse",
			"So": "Soja/-erzeugnisse"
		},
		"PriceAttendant": 4.3,
		"PriceGuest": 4.85,
		"PriceStudent": 3.7,
		"LactoseFree": true,
		"Vegan": true
	},
	{
		"Name": "LovleyVegiBowl, Tofu, Bulgur, Kimchi Gurke, Avocado, Kürbiskerne mit Wild Karachi & Wasabi Dressing (1, 2, 3, 5, 9, Gl, Ei, So, La, Sl, Sf, Se, Sw)",
		"Category": "Campus Spezial",
		"Date": "2020-07-14",
		"Additives": {
			"1": "Farbstoffe",
			"2": "Konservierungsstoffe",
			"3": "Antioxidationsmittel",
			"5": "Geschwefelt",
			"9": "Süßungsmittel",
			"Ei": "Ei/-erzeugnisse",
			"Gl": "Glutenhaltiges Getreide und daraus hergestellte Erzeugnissse",
			"La": "Milch/-erzeugnisse (einschl. Laktose)",
			"Se": "Sesam/-erzeugnisse",
			"Sf": "Senf/-erzeugnisse",
			"Sl": "Sellerie/-erzeugnisse",
			"So": "Soja/-erzeugnisse",
			"Sw": "Schwefeldioxid/Sulfite"
		},
		"PriceAttendant": 5.3,
		"PriceGuest": 6.35,
		"PriceStudent": 4.8,
		"Vegetarian": true
	},
	{
		"Name": "LovleyChickenBowl,Tomatenbulgur,Kimchi Gurke, Avocado, Kürbiskerne mit Wild Karachi & WasabiDressing (1, 2, 3, 5, 9, Gl, Ei, So, La, Sl, Sf, Se, Sw)",
		"Category": "Campus Spezial",
		"Date": "2020-07-14",
		"Additives": {
			"1": "Farbstoffe",
			"2": "Konservierungsstoffe",
			"3": "Antioxidationsmittel",
			"5": "Geschwefelt",
			"9": "Süßungsmittel",
			"Ei": "Ei/-erzeugnisse",
			"Gl": "Glutenhaltiges Getreide und daraus hergestellte Erzeugnissse",
			"La": "Milch/-erzeugnisse (einschl. Laktose)",
			"Se": "Sesam/-erzeugnisse",
			"Sf": "Senf/-erzeugnisse",
			"Sl": "Sellerie/-erzeugnisse",
			"So": "Soja/-erzeugnisse",
			"Sw": "Schwefeldioxid/Sulfite"
		},
		"PriceAttendant": 6.3,
		"PriceGuest": 7.9,
		"PriceStudent": 5.3,
		"Poultry": true
	}
]
