[
	{
		"Additives": {
			"Fi": "Fisch/-erzeugnisse",
			"Gl": "Glutenhaltiges Getreide und daraus hergestellte Erzeugnissse",
			"La": "Milch/-erzeugnisse (einschl. Laktose)",
			"Nu": "Schalenfrüchte/-erzeugnisse",
			"Sw": "Schwefeldioxid/Sulfite"
		},
		"Alcohol": false,
		"Beef": false,
		"Category": "Campus Spezial",
		"Date": "2020-08-28T00:00:00.000Z",
		"Fish": true,
		"LactoseFree": false,
		"Name": "Gebratenes Kabeljaufilet (Gl, Fi), mediterrane Tomaten-Gemüsesoße (La, Nu, Sw), Broccoli, Blechkartoffeln",
		"Pig": false,
		"Poultry": false,
		"PriceAttendant": 6.5,
		"PriceGuest": 8.15,
		"PriceStudent": 5.5,
		"Vegan": false,
		"Vegetarian": false
	},
	{
		"Additives": {
			"2": "Konservierungsstoffe",
			"Gl": "Glutenhaltiges Getreide und daraus hergestellte Erzeugnissse",
			"Sf": "Senf/-erzeugnisse",
			"Sl": "Sellerie/-erzeugnisse",
			"So": "Soja/-erzeugnisse",
			"Sw": "Schwefeldioxid/Sulfite"
		},
		"Alcohol": false,
		"Beef": false,
		"Category": "Vegetarisch",
		"Date": "2020-08-28T00:00:00.000Z",
		"Fish": false,
		"LactoseFree": true,
		"Name": "Gemüsepfanne in süß saurer Soße (2, Gl, So, Sl, Sf, Sw), Basmatireis",
		"Pig": false,
		"Poultry": false,
		"PriceAttendant": 4.2,
		"PriceGuest": 5.25,
		"PriceStudent": 2.9,
		"Vegan": true,
		"Vegetarian": false
	}
]
