[
	{
		"Name": "WarmBowl mit Reis, Edamame, Kürbis &amp; Kokos (So,Sl)",
		"Category": "Pottkieker",
		"Date": "2024-10-18",
		"Additives": {
			"Sl": "Sellerie und Sellerieerzeugnisse",
			"So": "Soja und Sojaerzeugnisse"
		},
		"PriceAttendant": 3.4,
		"PriceGuest": 4.1,
		"PriceStudent": 2.2,
		"LactoseFree": true,
		"Vegan": true
	},
	{
		"Name": "Gemüse-Bratling (Ei,Mi,GlW), , Gemüse in Rahm (So,Sl,GlW), , pikante Kartoffeln mit Sesam (Se)",
		"Category": "CampusKlassiker",
		"Date": "2024-10-18",
		"Additives": {
			"Ei": "Ei und Eierzeugnisse",
			"GlW": "glutenhaltiges Getreide und daraus hergestellte Erzeugnisse (Weizen)",
			"Mi": "Milch und Milcherzeugnisse (einschließlich Laktose)",
			"Se": "Sesamsamen und Sesamsamenerzeugnisse",
			"Sl": "Sellerie und Sellerieerzeugnisse",
			"So": "Soja und Sojaerzeugnisse"
		},
		"PriceAttendant": 4.1,
		"PriceGuest": 5.3,
		"PriceStudent": 2.8,
		"Vegetarian": true
	},
	{
		"Name": "Omelette (Ei,Mi), pikante Kartoffeln mit Sesam, Tomate &amp; Gurke (Se)",
		"Category": "CampusVital",
		"Date": "2024-10-18",
		"Additives": {
			"Ei": "Ei und Eierzeugnisse",
			"Mi": "Milch und Milcherzeugnisse (einschließlich Laktose)",
			"Se": "Sesamsamen und Sesamsamenerzeugnisse"
		},
		"PriceAttendant": 5.3,
		"PriceGuest": 6.5,
		"PriceStudent": 4.0,
		"Vegetarian": true
	}
]
