[
	{
		"Name": "glacierte rote Beete, Gemüsepfanne Texas (Gl), gedünsteter Kohlrabi, Ratatouille (Sl), Gemüse Bulgur (Gl, Sl), Djuvecreis",
		"Category": "Gemüse-Bar pro 100g",
		"Date": "2019-04-16",
		"Additives": {
			"Gl": "Glutenhaltiges Getreide und daraus hergestellte Erzeugnissse",
			"Sl": "Sellerie/-erzeugnisse"
		},
		"PriceAttendant": 0.8,
		"PriceGuest": 1.0,
		"PriceStudent": 0.6,
		"LactoseFree": true,
		"Vegan": true
	},
	{
		"Name": "Pasta \"Paprica\" Paprika mit grünem Pfeffer (So, Sl), Pasta (Gl)",
		"Category": "Pasta-Bar pro 100g",
		"Date": "2019-04-16",
		"Additives": {
			"Gl": "Glutenhaltiges Getreide und daraus hergestellte Erzeugnissse",
			"Sl": "Sellerie/-erzeugnisse",
			"So": "Soja/-erzeugnisse"
		},
		"PriceAttendant": 0.8,
		"PriceGuest": 1.0,
		"PriceStudent": 0.6,
		"LactoseFree": true,
		"Vegan": true
	},
	{
		"Name": "Pasta Arcobaleno mit Schinken und Käse (1, 2, 3, 8, La, Sl, Sw), Hartkäse (La), Pasta (Gl)",
		"Category": "Pasta-Bar pro 100g",
		"Date": "2019-04-16",
		"Additives": {
			"1": "Farbstoffe",
			"2": "Konservierungsstoffe",
			"3": "Antioxidationsmittel",
			"8": "Phosphat",
			"Gl": "Glutenhaltiges Getreide und daraus hergestellte Erzeugnissse",
			"La": "Milch/-erzeugnisse (einschl. Laktose)",
			"Sl": "Sellerie/-erzeugnisse",
			"Sw": "Schwefeldioxid/Sulfite"
		},
		"PriceAttendant": 0.8,
		"PriceGuest": 1.0,
		"PriceStudent": 0.6,
		"Pig": true
	},
	{
		"Name": "Warmer Apfelstrudel (Gl), Vanillesoße (La)",
		"Category": "Aus dem Suppentopf und Süßes",
		"Date": "2019-04-16",
		"Additives": {
			"Gl": "Glutenhaltiges Getreide und daraus hergestellte Erzeugnissse",
			"La": "Milch/-erzeugnisse (einschl. Laktose)"
		},
		"PriceAttendant": 2.6,
		"PriceGuest": 3.25,
		"PriceStudent": 1.4,
		"Vegetarian": true
	},
	{
		"Name": "Indische Currycremesuppe mit Kürbis (La, Sl, Sf)",
		"Category": "Aus dem Suppentopf und Süßes",
		"Date": "2019-04-16",
		"Additives": {
			"La": "Milch/-erzeugnisse (einschl. Laktose)",
			"Sf": "Senf/-erzeugnisse",
			"Sl": "Sellerie/-erzeugnisse"
		},
		"PriceAttendant": 2.6,
		"PriceGuest": 3.25,
		"PriceStudent": 1.4,
		"Vegetarian": true
	},
	{
		"Name": "Rindfleischfrikadelle (Gl, Ei), Bayrischer Kartoffelsalat mit Gurken (2, Sf), Senf (Sf)",
		"Category": "Gut und günstig",
		"Date": "2019-04-16",
		"Additives": {
			"2": "Konservierungsstoffe",
			"Ei": "Ei/-erzeugnisse",
			"Gl": "Glutenhaltiges Getreide und daraus hergestellte Erzeugnissse",
			"Sf": "Senf/-erzeugnisse"
		},
		"PriceAttendant": 3.5,
		"PriceGuest": 4.4,
		"PriceStudent": 2.2,
		"Beef": true,
		"LactoseFree": true
	},
	{
		"Name": "Käsespätzle mit Zwiebelschmelze (Gl, Ei, La), gemischte Blattsalate (Sw), hausgemachtes Joghurt Dressing (La)",
		"Category": "Vegetarisch",
		"Date": "2019-04-16",
		"Additives": {
			"Ei": "Ei/-erzeugnisse",
			"Gl": "Glutenhaltiges Getreide und daraus hergestellte Erzeugnissse",
			"La": "Milch/-erzeugnisse (einschl. Laktose)",
			"Sw": "Schwefeldioxid/Sulfite"
		},
		"PriceAttendant": 4.0,
		"PriceGuest": 5.0,
		"PriceStudent": 2.7,
		"Vegetarian": true
	},
	{
		"Name": "Hähnchenschnitzel im Knuspermantel (Gl), Bayrischer Kartoffelsalat mit Gurken (2, Sf)",
		"Category": "Beliebt und gerne gegessen",
		"Date": "2019-04-16",
		"Additives": {
			"2": "Konservierungsstoffe",
			"Gl": "Glutenhaltiges Getreide und daraus hergestellte Erzeugnissse",
			"Sf": "Senf/-erzeugnisse"
		},
		"PriceAttendant": 4.25,
		"PriceGuest": 5.35,
		"PriceStudent": 2.95,
		"LactoseFree": true,
		"Poultry": true
	},
	{
		"Name": "Entenbrustfilet, Pfefferrahmsoße mit Mango-Chutney (Gl, La, Sl), Mandelbroccoli (La, Nu), Schupfnudeln (Gl, Ei)",
		"Category": "Campus Spezial",
		"Date": "2019-04-16",
		"Additives": {
			"Ei": "Ei/-erzeugnisse",
			"Gl": "Glutenhaltiges Getreide und daraus hergestellte Erzeugnissse",
			"La": "Milch/-erzeugnisse (einschl. Laktose)",
			"Nu": "Schalenfrüchte/-erzeugnisse",
			"Sl": "Sellerie/-erzeugnisse"
		},
		"PriceAttendant": 6.3,
		"PriceGuest": 7.9,
		"PriceStudent": 5.3,
		"Poultry": true
	}
]
