[
	{
		"Additives": {
			"4": "Geschmacksverstärker",
			"Ei": "Ei/-erzeugnisse",
			"La": "Milch/-erzeugnisse (einschl. Laktose)",
			"Sf": "Senf/-erzeugnisse"
		},
		"Beef": false,
		"Date": "2018-08-31T00:00:00.000Z",
		"Fish": false,
		"LactoseFree": false,
		"Name": "3 Kartoffeltaschen mit Kräuter Frischkäsefüllung (La), Sourcreme (4, Ei, La, Sf), Zucchinisalat",
		"Pig": false,
		"Poultry": false,
		"PriceAttendant": 4.4,
		"PriceGuest": 5.5,
		"PriceStudent": 3.1,
		"Vegan": false,
		"Vegetarian": true
	},
	{
		"Additives": {
			"5": "Geschwefelt",
			"Ei": "Ei/-erzeugnisse",
			"Gl": "Glutenhaltiges Getreide und daraus hergestellte Erzeugnissse",
			"La": "Milch/-erzeugnisse (einschl. Laktose)",
			"Nu": "Schalenfrüchte/-erzeugnisse",
			"Sw": "Schwefeldioxid/Sulfite"
		},
		"Beef": false,
		"Date": "2018-08-31T00:00:00.000Z",
		"Fish": false,
		"LactoseFree": false,
		"Name": "Mandelbroccoli (La, Nu), Karotten Pastinakenmix mit frischer Petersilie, gebratene Paprika (5, Sw), Auberginen mit Balsamico Bianco (5, Sw), Schupfnudeln (Gl, Ei)",
		"Pig": false,
		"Poultry": false,
		"PriceAttendant": 0.8,
		"PriceGuest": 1,
		"PriceStudent": 0.6,
		"Vegan": false,
		"Vegetarian": true
	},
	{
		"Additives": {
			"Ei": "Ei/-erzeugnisse",
			"Gl": "Glutenhaltiges Getreide und daraus hergestellte Erzeugnissse",
			"La": "Milch/-erzeugnisse (einschl. Laktose)",
			"Sf": "Senf/-erzeugnisse"
		},
		"Beef": false,
		"Date": "2018-08-31T00:00:00.000Z",
		"Fish": false,
		"LactoseFree": false,
		"Name": "Paniertes Schweineschnitzel (Gl, Ei, La), Paprikarahmsoße (Gl, La), Pommes Frites (Sf)",
		"Pig": true,
		"Poultry": false,
		"PriceAttendant": 4.25,
		"PriceGuest": 5.35,
		"PriceStudent": 2.95,
		"Vegan": false,
		"Vegetarian": false
	},
	{
		"Additives": {
			"2": "Konservierungsstoffe",
			"3": "Antioxidationsmittel",
			"8": "Phosphat",
			"Gl": "Glutenhaltiges Getreide und daraus hergestellte Erzeugnissse"
		},
		"Beef": false,
		"Date": "2018-08-31T00:00:00.000Z",
		"Fish": false,
		"LactoseFree": true,
		"Name": "Pasta Boscaiola mit Mischpilzen und Speck (2, 3, 8), Eliche (Gl)",
		"Pig": true,
		"Poultry": false,
		"PriceAttendant": 0.8,
		"PriceGuest": 1,
		"PriceStudent": 0.6,
		"Vegan": false,
		"Vegetarian": false
	},
	{
		"Additives": {
			"6": "Geschwärzt",
			"Gl": "Glutenhaltiges Getreide und daraus hergestellte Erzeugnissse",
			"La": "Milch/-erzeugnisse (einschl. Laktose)",
			"Sf": "Senf/-erzeugnisse"
		},
		"Beef": false,
		"Date": "2018-08-31T00:00:00.000Z",
		"Fish": false,
		"LactoseFree": false,
		"Name": "Pasta mit Spinat und Olivenöl (6, La, Sf), Eliche (Gl)",
		"Pig": false,
		"Poultry": false,
		"PriceAttendant": 0.8,
		"PriceGuest": 1,
		"PriceStudent": 0.6,
		"Vegan": false,
		"Vegetarian": true
	},
	{
		"Additives": {
			"Sl": "Sellerie/-erzeugnisse"
		},
		"Beef": false,
		"Date": "2018-08-31T00:00:00.000Z",
		"Fish": false,
		"LactoseFree": true,
		"Name": "Vegane tomatisierte Linsensuppe (Sl)",
		"Pig": false,
		"Poultry": false,
		"PriceAttendant": 2.6,
		"PriceGuest": 3.25,
		"PriceStudent": 1.4,
		"Vegan": true,
		"Vegetarian": false
	},
	{
		"Additives": {
			"Gl": "Glutenhaltiges Getreide und daraus hergestellte Erzeugnissse",
			"Sl": "Sellerie/-erzeugnisse"
		},
		"Beef": true,
		"Date": "2018-08-31T00:00:00.000Z",
		"Fish": false,
		"LactoseFree": true,
		"Name": "Zucchini Hackfleischtopf (Sl), Penne (Gl)",
		"Pig": false,
		"Poultry": false,
		"PriceAttendant": 3.5,
		"PriceGuest": 4.4,
		"PriceStudent": 2.2,
		"Vegan": false,
		"Vegetarian": false
	}
]
