[
	{
		"Name": "Bratkartoffeln, Kräuterrührei (16, 20)",
		"Category": "",
		"Date": "2018-01-02",
		"Additives": {
			"16": "Ei/-erzeugnisse",
			"20": "Milch/-erzeugnisse (einschl. Laktose)"
		},
		"PriceAttendant": 3.35,
		"PriceGuest": 4.2,
		"PriceStudent": 2.05,
		"Vegetarian": true
	},
	{
		"Name": "Hamburger mit Tomate, Gurke und Salat (1, 2, 3, 9, 14, 16, 23, 24)",
		"Category": "",
		"Date": "2018-01-02",
		"Additives": {
			"1": "Farbstoffe",
			"14": "Glutenhaltiges Getreide",
			"16": "Ei/-erzeugnisse",
			"2": "Konservierungsstoffe",
			"23": "Senf/-erzeugnisse",
			"24": "Sesam/-erzeugnisse",
			"3": "Antioxidationsmittel",
			"9": "Süßungsmittel"
		},
		"PriceAttendant": 3.55,
		"PriceGuest": 4.5,
		"PriceStudent": 2.4,
		"Beef": true,
		"LactoseFree": true
	},
	{
		"Name": "Thai Chicken (17, 19, 22), Reis",
		"Category": "",
		"Date": "2018-01-02",
		"Additives": {
			"17": "Fisch/-erzeugnisse",
			"19": "Soja/-erzeugnisse",
			"22": "Sellerie/-erzeugnisse"
		},
		"PriceAttendant": 4.5,
		"PriceGuest": 5.65,
		"PriceStudent": 3.5,
		"Fish": true,
		"LactoseFree": true,
		"Poultry": true
	}
]
