[
	{
		"Name": "Spinatsuppe mit Gemüse & Kokos (So, Sl)",
		"Category": "Aus dem Suppentopf und Süßes",
		"Date": "2019-05-09",
		"Additives": {
			"Sl": "Sellerie/-erzeugnisse",
			"So": "Soja/-erzeugnisse"
		},
		"PriceAttendant": 2.6,
		"PriceGuest": 3.25,
		"PriceStudent": 1.4,
		"LactoseFree": true,
		"Vegan": true
	},
	{
		"Name": "Germknödel (Gl, Ei, La), Vanillesoße (La)",
		"Category": "Aus dem Suppentopf und Süßes",
		"Date": "2019-05-09",
		"Additives": {
			"Ei": "Ei/-erzeugnisse",
			"Gl": "Glutenhaltiges Getreide und daraus hergestellte Erzeugnissse",
			"La": "Milch/-erzeugnisse (einschl. Laktose)"
		},
		"PriceAttendant": 2.6,
		"PriceGuest": 3.25,
		"PriceStudent": 1.4,
		"Vegetarian": true
	},
	{
		"Name": "Currybratwurst (3, 4, 8, Sf), BBQ-Grillsoße (9, Sl, Sf), Pommes Frites (Sf)",
		"Category": "Beliebt und gerne gegessen",
		"Date": "2019-05-09",
		"Additives": {
			"3": "Antioxidationsmittel",
			"4": "Geschmacksverstärker",
			"8": "Phosphat",
			"9": "Süßungsmittel",
			"Sf": "Senf/-erzeugnisse",
			"Sl": "Sellerie/-erzeugnisse"
		},
		"PriceAttendant": 3.95,
		"PriceGuest": 4.95,
		"PriceStudent": 2.65,
		"LactoseFree": true,
		"Pig": true
	},
	{
		"Name": "Hähnchenbrust mit Tomate & Mozzarella (So, La), Pesto-Sahnesoße (La, Nu), Brokkoli, Reis",
		"Category": "Campus Spezial",
		"Date": "2019-05-09",
		"Additives": {
			"La": "Milch/-erzeugnisse (einschl. Laktose)",
			"Nu": "Schalenfrüchte/-erzeugnisse",
			"So": "Soja/-erzeugnisse"
		},
		"PriceAttendant": 4.7,
		"PriceGuest": 5.9,
		"PriceStudent": 3.7,
		"Poultry": true
	},
	{
		"Name": "***100 JAHRE WISSENSWERFT*** 2 Kürbis-Steckrüben-Bratlinge (Gl), bunter Spinatsalat, Frühlingszwiebel-Quark (La)",
		"Category": "Campus Spezial",
		"Date": "2019-05-09",
		"Additives": {
			"Gl": "Glutenhaltiges Getreide und daraus hergestellte Erzeugnissse",
			"La": "Milch/-erzeugnisse (einschl. Laktose)"
		},
		"PriceAttendant": 4.75,
		"PriceGuest": 5.95,
		"PriceStudent": 3.75,
		"Vegetarian": true
	}
]
