[
	{
		"Additives": {
			"1": "Farbstoffe",
			"Sf": "Senf/-erzeugnisse",
			"So": "Soja/-erzeugnisse"
		},
		"Alcohol": false,
		"Beef": false,
		"Category": "Campus Spezial",
		"Date": "2020-12-03T00:00:00.000Z",
		"Fish": false,
		"LactoseFree": true,
		"Name": "Wir kochen was Sie lieben..., Putenoberkeule``Asia`` auf Wokgemüse (1, So, Sf), Curryreis (Sf)",
		"Pig": false,
		"Poultry": true,
		"PriceAttendant": 5.5,
		"PriceGuest": 6.9,
		"PriceStudent": 4.5,
		"Vegan": false,
		"Vegetarian": false
	},
	{
		"Additives": {
			"Ei": "Ei/-erzeugnisse",
			"Gl": "Glutenhaltiges Getreide und daraus hergestellte Erzeugnissse",
			"La": "Milch/-erzeugnisse (einschl. Laktose)"
		},
		"Alcohol": false,
		"Beef": false,
		"Category": "Vegetarisch",
		"Date": "2020-12-03T00:00:00.000Z",
		"Fish": false,
		"LactoseFree": false,
		"Name": "Gemüseauflauf Palermo (Gl, Ei, La), Hausgemachte Käsesoße (Gl, La)",
		"Pig": false,
		"Poultry": false,
		"PriceAttendant": 3.9,
		"PriceGuest": 4.9,
		"PriceStudent": 2.6,
		"Vegan": false,
		"Vegetarian": true
	},
	{
		"Additives": {
			"Ei": "Ei/-erzeugnisse",
			"Gl": "Glutenhaltiges Getreide und daraus hergestellte Erzeugnissse",
			"La": "Milch/-erzeugnisse (einschl. Laktose)",
			"Sw": "Schwefeldioxid/Sulfite"
		},
		"Alcohol": false,
		"Beef": false,
		"Category": "Vegetarisch",
		"Date": "2020-12-03T00:00:00.000Z",
		"Fish": false,
		"LactoseFree": false,
		"Name": "Käsespätzle mit Zwiebelschmelze (Gl, Ei, La), gemischte Blattsalate (Sw), hausgemachtes Joghurt Dressing (La)",
		"Pig": false,
		"Poultry": false,
		"PriceAttendant": 4.4,
		"PriceGuest": 5.5,
		"PriceStudent": 3.1,
		"Vegan": false,
		"Vegetarian": true
	}
]
