[
  {
    "Name": "Gratiniertes Bruscetta (Gl,La,Sf,Sw)",
    "Category": "Pastabar",
    "Date": "2022-06-22T00:00:00Z",
    "Additives": {
      "Gl": "glutenhaltiges Getreide und daraus hergestellte Erzeugnisse (z. B. Weizen, Roggen, Gerste etc.)",
      "La": "Milch und Milcherzeugnisse (einschl. Laktose)",
      "Sf": "Senf und Senferzeugnisse",
      "Sw": "Schwefeldioxid und Sulfite (Konzentration über 10mg/kg oder 10mg/l)"
    },
    "PriceAttendant": 0.9,
    "PriceGuest": 1.1,
    "PriceStudent": 0.7,
    "Vegetarian": true
  },
  {
    "Name": "Vegane Soja-Chunks in asiatischer Tomatensoße (2,Gl,So,Se), Reis",
    "Category": "Pastabar",
    "Date": "2022-06-22T00:00:00Z",
    "Additives": {
      "2": "Konservierungsstoff",
      "Gl": "glutenhaltiges Getreide und daraus hergestellte Erzeugnisse (z. B. Weizen, Roggen, Gerste etc.)",
      "Se": "Sesamsamen und Sesamsamenerzeugnisse",
      "So": "Soja und Sojaerzeugnisse"
    },
    "PriceAttendant": 0.9,
    "PriceGuest": 1.1,
    "PriceStudent": 0.7,
    "LactoseFree": true,
    "Vegan": true
  },
  {
    "Name": "Cremige Soße mit Speck und Wirsing (2,3,8,Gl,La), Schupfnudeln (Gl,Ei)",
    "Category": "Pastabar",
    "Date": "2022-06-22T00:00:00Z",
    "Additives": {
      "2": "Konservierungsstoff",
      "3": "Antioxidationsmittel",
      "8": "Phosphat",
      "Ei": "Ei und Eierzeugnisse",
      "Gl": "glutenhaltiges Getreide und daraus hergestellte Erzeugnisse (z. B. Weizen, Roggen, Gerste etc.)",
      "La": "Milch und Milcherzeugnisse (einschl. Laktose)"
    },
    "PriceAttendant": 0.9,
    "PriceGuest": 1.1,
    "PriceStudent": 0.7,
    "Pig": true
  },
  {
    "Name": "Geflügelcurry mit Mandeln (Gl,La,Nu,Sf)",
    "Category": "CampusKlassiker",
    "Date": "2022-06-22T00:00:00Z",
    "Additives": {
      "Gl": "glutenhaltiges Getreide und daraus hergestellte Erzeugnisse (z. B. Weizen, Roggen, Gerste etc.)",
      "La": "Milch und Milcherzeugnisse (einschl. Laktose)",
      "Nu": "Schalenfrüchte (z.B. Mandel, Haselnüsse, Walnuss etc.)/-erzeugnisse",
      "Sf": "Senf und Senferzeugnisse"
    },
    "PriceAttendant": 3.75,
    "PriceGuest": 4.85,
    "PriceStudent": 2.5,
    "Poultry": true
  },
  {
    "Name": "Crepe mit Gemüse-Hummusfüllung (Gl,Ei,La,Sl,Se), Salsa Dip (1,2,3,4,9,Ei,La,Sf)",
    "Category": "CampusVital",
    "Date": "2022-06-22T00:00:00Z",
    "Additives": {
      "1": "Farbstoff",
      "2": "Konservierungsstoff",
      "3": "Antioxidationsmittel",
      "4": "Geschmacksverstärker",
      "9": "Süßungsmittel",
      "Ei": "Ei und Eierzeugnisse",
      "Gl": "glutenhaltiges Getreide und daraus hergestellte Erzeugnisse (z. B. Weizen, Roggen, Gerste etc.)",
      "La": "Milch und Milcherzeugnisse (einschl. Laktose)",
      "Se": "Sesamsamen und Sesamsamenerzeugnisse",
      "Sf": "Senf und Senferzeugnisse",
      "Sl": "Sellerie und Sellerieerzeugnisse"
    },
    "PriceAttendant": 4.15,
    "PriceGuest": 5.25,
    "PriceStudent": 2.9,
    "Vegetarian": true
  },
  {
    "Name": "Bratreis mit Ei und Frühlingszwiebeln (Ei), frisches Gemüse (2,Sw), rote Currysoße (Sl)",
    "Category": "CampusWorld",
    "Date": "2022-06-22T00:00:00Z",
    "Additives": {
      "2": "Konservierungsstoff",
      "Ei": "Ei und Eierzeugnisse",
      "Sl": "Sellerie und Sellerieerzeugnisse",
      "Sw": "Schwefeldioxid und Sulfite (Konzentration über 10mg/kg oder 10mg/l)"
    },
    "PriceAttendant": 4.3,
    "PriceGuest": 5.5,
    "PriceStudent": 3.0,
    "LactoseFree": true,
    "Vegetarian": true
  },
  {
    "Name": "Meins - Caponata mit Auberginen, Tomaten, Zucchini und Kapern (3,5,Sl,Sw), Gnocchi",
    "Category": "Highlight",
    "Date": "2022-06-22T00:00:00Z",
    "Additives": {
      "3": "Antioxidationsmittel",
      "5": "Geschwefelt",
      "Sl": "Sellerie und Sellerieerzeugnisse",
      "Sw": "Schwefeldioxid und Sulfite (Konzentration über 10mg/kg oder 10mg/l)"
    },
    "PriceAttendant": 5.8,
    "PriceGuest": 7.0,
    "PriceStudent": 4.5,
    "LactoseFree": true,
    "Vegan": true
  }
]
