[
	{
		"Name": "Kürbissuppe mit Kokos & Ingwer (Gl, Sl)",
		"Category": "Aus dem Suppentopf und Süßes",
		"Date": "2019-02-06",
		"Additives": {
			"Gl": "Glutenhaltiges Getreide und daraus hergestellte Erzeugnissse",
			"Sl": "Sellerie/-erzeugnisse"
		},
		"PriceAttendant": 2.6,
		"PriceGuest": 3.25,
		"PriceStudent": 1.4,
		"LactoseFree": true,
		"Vegan": true
	},
	{
		"Name": "Penne mit Tomaten, Chili & Tofu (6, Gl, So)",
		"Category": "Gut und günstig",
		"Date": "2019-02-06",
		"Additives": {
			"6": "Geschwärzt",
			"Gl": "Glutenhaltiges Getreide und daraus hergestellte Erzeugnissse",
			"So": "Soja/-erzeugnisse"
		},
		"PriceAttendant": 3.35,
		"PriceGuest": 4.2,
		"PriceStudent": 2.05,
		"LactoseFree": true,
		"Vegan": true
	},
	{
		"Name": "Hähnchenkeule (Sf), pikante Paprika-Salsa (4), Pommes Frites (Sf)",
		"Category": "Beliebt und gerne gegessen",
		"Date": "2019-02-06",
		"Additives": {
			"4": "Geschmacksverstärker",
			"Sf": "Senf/-erzeugnisse"
		},
		"PriceAttendant": 3.95,
		"PriceGuest": 4.95,
		"PriceStudent": 2.65,
		"LactoseFree": true,
		"Poultry": true
	},
	{
		"Name": "Pulled Pork Burger mit BBQ-Soße (3, Gl, Sf), Cole-Slaw-Salat (La), Pommes Frites (Sf)",
		"Category": "Campus Spezial",
		"Date": "2019-02-06",
		"Additives": {
			"3": "Antioxidationsmittel",
			"Gl": "Glutenhaltiges Getreide und daraus hergestellte Erzeugnissse",
			"La": "Milch/-erzeugnisse (einschl. Laktose)",
			"Sf": "Senf/-erzeugnisse"
		},
		"PriceAttendant": 5.75,
		"PriceGuest": 7.2,
		"PriceStudent": 4.75,
		"Pig": true
	}
]
