[
	{
		"Additives": {
			"2": "Konservierungsstoffe",
			"Gl": "Glutenhaltiges Getreide und daraus hergestellte Erzeugnissse",
			"Sf": "Senf/-erzeugnisse",
			"Sl": "Sellerie/-erzeugnisse"
		},
		"Beef": false,
		"Date": "2018-10-11T00:00:00.000Z",
		"Fish": false,
		"LactoseFree": true,
		"Name": "Hähnchen-Nuggets (Gl), Ananas-Chili-Soße (2, Sl, Sf)",
		"Pig": false,
		"Poultry": true,
		"PriceAttendant": 3.5,
		"PriceGuest": 4.4,
		"PriceStudent": 2.35,
		"Vegan": false,
		"Vegetarian": false
	},
	{
		"Additives": {
			"Sf": "Senf/-erzeugnisse",
			"So": "Soja/-erzeugnisse"
		},
		"Beef": false,
		"Date": "2018-10-11T00:00:00.000Z",
		"Fish": false,
		"LactoseFree": true,
		"Name": "Indischer Dal mit roten Linsen, Kartoffeln & Spinat (So, Sf), Reis",
		"Pig": false,
		"Poultry": false,
		"PriceAttendant": 3.85,
		"PriceGuest": 4.85,
		"PriceStudent": 2.55,
		"Vegan": true,
		"Vegetarian": false
	},
	{
		"Additives": {
			"Gl": "Glutenhaltiges Getreide und daraus hergestellte Erzeugnissse"
		},
		"Beef": true,
		"Date": "2018-10-11T00:00:00.000Z",
		"Fish": false,
		"LactoseFree": true,
		"Name": "Schweinekrustenbraten, Röstzwiebelsoße (Gl)",
		"Pig": true,
		"Poultry": false,
		"PriceAttendant": 3.55,
		"PriceGuest": 4.5,
		"PriceStudent": 2.85,
		"Vegan": false,
		"Vegetarian": false
	},
	{
		"Additives": {
			"3": "Antioxidationsmittel",
			"Gl": "Glutenhaltiges Getreide und daraus hergestellte Erzeugnissse",
			"Sl": "Sellerie/-erzeugnisse",
			"So": "Soja/-erzeugnisse"
		},
		"Beef": false,
		"Date": "2018-10-11T00:00:00.000Z",
		"Fish": false,
		"LactoseFree": true,
		"Name": "Süßkartoffelsuppe mit Paprika & Mais (3, Gl, So, Sl)",
		"Pig": false,
		"Poultry": false,
		"PriceAttendant": 2.6,
		"PriceGuest": 3.25,
		"PriceStudent": 1.4,
		"Vegan": true,
		"Vegetarian": false
	}
]
