[
	{
		"Additives": {
			"19": "Soja/-erzeugnisse",
			"25": "Schwefeldioxid/Sulfite"
		},
		"Beef": false,
		"Date": "2018-04-12T00:00:00.000Z",
		"Fish": false,
		"LactoseFree": true,
		"Name": "Hähnchenbrust (19), Tomaten-Paprika-Gemüse mit Apfel & Bambus (25), Reis-Mix",
		"Pig": false,
		"Poultry": true,
		"PriceAttendant": 4.45,
		"PriceGuest": 5.6,
		"PriceStudent": 3.15,
		"Vegan": false,
		"Vegetarian": false
	},
	{
		"Additives": {
			"20": "Milch/-erzeugnisse (einschl. Laktose)",
			"3": "Antioxidationsmittel",
			"6": "Geschwärzt"
		},
		"Beef": false,
		"Date": "2018-04-12T00:00:00.000Z",
		"Fish": false,
		"LactoseFree": false,
		"Name": "Kartoffelrösti (3), Pfannengemüse (6), Koriander-Joghurt (20)",
		"Pig": false,
		"Poultry": false,
		"PriceAttendant": 3.85,
		"PriceGuest": 4.85,
		"PriceStudent": 2.55,
		"Vegan": false,
		"Vegetarian": true
	},
	{
		"Additives": {
			"19": "Soja/-erzeugnisse",
			"22": "Sellerie/-erzeugnisse",
			"3": "Antioxidationsmittel"
		},
		"Beef": false,
		"Date": "2018-04-12T00:00:00.000Z",
		"Fish": false,
		"LactoseFree": true,
		"Name": "Kokos-Tomaten-Suppe (3, 19, 22)",
		"Pig": false,
		"Poultry": false,
		"PriceAttendant": 2.6,
		"PriceGuest": 3.25,
		"PriceStudent": 1.4,
		"Vegan": true,
		"Vegetarian": false
	},
	{
		"Additives": {
			"20": "Milch/-erzeugnisse (einschl. Laktose)",
			"22": "Sellerie/-erzeugnisse",
			"25": "Schwefeldioxid/Sulfite"
		},
		"Beef": true,
		"Date": "2018-04-12T00:00:00.000Z",
		"Fish": false,
		"LactoseFree": false,
		"Name": "Rinderbraten (22, 25), Champignon-Pfefferrahmsoße (20, 25)",
		"Pig": false,
		"Poultry": false,
		"PriceAttendant": 4.55,
		"PriceGuest": 5.75,
		"PriceStudent": 3.85,
		"Vegan": false,
		"Vegetarian": false
	}
]
