[
	{
		"Additives": {
			"3": "Antioxidationsmittel",
			"Ei": "Ei/-erzeugnisse",
			"Gl": "Glutenhaltiges Getreide und daraus hergestellte Erzeugnissse"
		},
		"Beef": false,
		"Category": "Aus dem Suppentopf und Süßes",
		"Date": "2019-04-05T00:00:00.000Z",
		"Fish": false,
		"LactoseFree": true,
		"Name": "3 Kartoffelpuffer (Gl, Ei), Apfelmus (3)",
		"Pig": false,
		"Poultry": false,
		"PriceAttendant": 2.6,
		"PriceGuest": 3.25,
		"PriceStudent": 1.4,
		"Vegan": false,
		"Vegetarian": true
	},
	{
		"Additives": {
			"Gl": "Glutenhaltiges Getreide und daraus hergestellte Erzeugnissse",
			"La": "Milch/-erzeugnisse (einschl. Laktose)"
		},
		"Beef": true,
		"Category": "Aus dem Suppentopf und Süßes",
		"Date": "2019-04-05T00:00:00.000Z",
		"Fish": false,
		"LactoseFree": false,
		"Name": "Pikante Gulaschsuppe mit Rindfleisch, Kartoffeln & Paprika (Gl, La)",
		"Pig": false,
		"Poultry": false,
		"PriceAttendant": 2.6,
		"PriceGuest": 3.25,
		"PriceStudent": 1.4,
		"Vegan": false,
		"Vegetarian": false
	},
	{
		"Additives": {
			"Gl": "Glutenhaltiges Getreide und daraus hergestellte Erzeugnissse",
			"La": "Milch/-erzeugnisse (einschl. Laktose)",
			"Sf": "Senf/-erzeugnisse"
		},
		"Beef": true,
		"Category": "Beliebt und gerne gegessen",
		"Date": "2019-04-05T00:00:00.000Z",
		"Fish": false,
		"LactoseFree": false,
		"Name": "Paniertes Schweineschnitzel (Gl), Champignonrahmsoße (La), Pommes Frites (Sf)",
		"Pig": true,
		"Poultry": false,
		"PriceAttendant": 4.25,
		"PriceGuest": 5.35,
		"PriceStudent": 2.95,
		"Vegan": false,
		"Vegetarian": false
	},
	{
		"Additives": {
			"2": "Konservierungsstoffe",
			"Gl": "Glutenhaltiges Getreide und daraus hergestellte Erzeugnissse",
			"Kr": "Krebstier(e)/-erzeugnisse",
			"Sl": "Sellerie/-erzeugnisse",
			"So": "Soja/-erzeugnisse",
			"Sw": "Schwefeldioxid/Sulfite"
		},
		"Beef": false,
		"Category": "Campus Spezial",
		"Date": "2019-04-05T00:00:00.000Z",
		"Fish": false,
		"LactoseFree": true,
		"Name": "Wir kochen, was Sie lieben..., Gebackene Garnelen auf Gemüse Thai Green (2, Gl, Kr, So, Sl, Sw), Reis-Mix",
		"Pig": false,
		"Poultry": false,
		"PriceAttendant": 4.75,
		"PriceGuest": 5.95,
		"PriceStudent": 3.75,
		"Vegan": false,
		"Vegetarian": false
	},
	{
		"Additives": {
			"So": "Soja/-erzeugnisse"
		},
		"Beef": false,
		"Category": "Gut und günstig",
		"Date": "2019-04-05T00:00:00.000Z",
		"Fish": false,
		"LactoseFree": true,
		"Name": "Chili con Soja mit Bohnen & Mais (So), Reis-Mix",
		"Pig": false,
		"Poultry": false,
		"PriceAttendant": 3.35,
		"PriceGuest": 4.2,
		"PriceStudent": 2.05,
		"Vegan": true,
		"Vegetarian": false
	}
]
