[
	{
		"Additives": {
			"Sl": "Sellerie/-erzeugnisse",
			"So": "Soja/-erzeugnisse"
		},
		"Beef": false,
		"Category": "Aus dem Suppentopf und Süßes",
		"Date": "2019-07-15T00:00:00.000Z",
		"Fish": false,
		"LactoseFree": true,
		"Name": "Karottensuppe mit Mango & Kokos (So, Sl)",
		"Pig": false,
		"Poultry": false,
		"PriceAttendant": 2.6,
		"PriceGuest": 3.25,
		"PriceStudent": 1.4,
		"Vegan": true,
		"Vegetarian": false
	},
	{
		"Additives": {
			"Ei": "Ei/-erzeugnisse",
			"Gl": "Glutenhaltiges Getreide und daraus hergestellte Erzeugnissse",
			"La": "Milch/-erzeugnisse (einschl. Laktose)"
		},
		"Beef": false,
		"Category": "Beliebt und gerne gegessen",
		"Date": "2019-07-15T00:00:00.000Z",
		"Fish": false,
		"LactoseFree": false,
		"Name": "Paniertes Schweineschnitzel (Gl, Ei, La), Paprikarahmsoße (Gl, La), Kartoffelkroketten (Gl)",
		"Pig": true,
		"Poultry": false,
		"PriceAttendant": 4.65,
		"PriceGuest": 5.85,
		"PriceStudent": 3.35,
		"Vegan": false,
		"Vegetarian": false
	},
	{
		"Additives": {
			"Fi": "Fisch/-erzeugnisse",
			"Gl": "Glutenhaltiges Getreide und daraus hergestellte Erzeugnissse",
			"La": "Milch/-erzeugnisse (einschl. Laktose)"
		},
		"Beef": false,
		"Category": "Campus Spezial",
		"Date": "2019-07-15T00:00:00.000Z",
		"Fish": true,
		"LactoseFree": false,
		"Name": "Seelachsfilet mit Käse-Kruste (Fi, La), Tomatenragout, Brokkoli, Nudeln (Gl)",
		"Pig": false,
		"Poultry": false,
		"PriceAttendant": 5.95,
		"PriceGuest": 7.45,
		"PriceStudent": 4.95,
		"Vegan": false,
		"Vegetarian": false
	},
	{
		"Additives": {
			"2": "Konservierungsstoffe",
			"Gl": "Glutenhaltiges Getreide und daraus hergestellte Erzeugnissse",
			"Sf": "Senf/-erzeugnisse",
			"Sl": "Sellerie/-erzeugnisse",
			"So": "Soja/-erzeugnisse"
		},
		"Beef": false,
		"Category": "Vegetarisch",
		"Date": "2019-07-15T00:00:00.000Z",
		"Fish": false,
		"LactoseFree": true,
		"Name": "Mini-Frühlingsrollen (Gl, So), Ananas-Chili-Soße (2, Sl, Sf), Asiagemüse (2, Gl, So)",
		"Pig": false,
		"Poultry": false,
		"PriceAttendant": 3.9,
		"PriceGuest": 4.9,
		"PriceStudent": 2.75,
		"Vegan": true,
		"Vegetarian": false
	}
]
