[
	{
		"Name": "Asiatisches Gemüse mit Mi-Nudeln, mini Wrap (2, Gl, Ei, So, Nu, Se), Dessert (Gl, La)",
		"Category": "Vegetarisch",
		"Date": "2020-07-21",
		"Additives": {
			"2": "Konservierungsstoffe",
			"Ei": "Ei/-erzeugnisse",
			"Gl": "Glutenhaltiges Getreide und daraus hergestellte Erzeugnissse",
			"La": "Milch/-erzeugnisse (einschl. Laktose)",
			"Nu": "Schalenfrüchte/-erzeugnisse",
			"Se": "Sesam/-erzeugnisse",
			"So": "Soja/-erzeugnisse"
		},
		"PriceAttendant": 4.8,
		"PriceGuest": 6.0,
		"PriceStudent": 3.5,
		"Vegetarian": true
	},
	{
		"Name": "Asiatisches Gemüse mit Mi-Nudeln und Hähnchenfleisch (2, Gl, Ei, So, Nu), Dessert (Gl, La)",
		"Category": "Campus Spezial",
		"Date": "2020-07-21",
		"Additives": {
			"2": "Konservierungsstoffe",
			"Ei": "Ei/-erzeugnisse",
			"Gl": "Glutenhaltiges Getreide und daraus hergestellte Erzeugnissse",
			"La": "Milch/-erzeugnisse (einschl. Laktose)",
			"Nu": "Schalenfrüchte/-erzeugnisse",
			"So": "Soja/-erzeugnisse"
		},
		"PriceAttendant": 5.4,
		"PriceGuest": 6.75,
		"PriceStudent": 4.4,
		"Poultry": true
	}
]
