[
  {
    "Name": "Veganer Steckrübeneintopf mit einem Brötchen (Gl,Sl,Sw)",
    "Category": "CampusSpezial",
    "Date": "2021-11-25T00:00:00Z",
    "Additives": {
      "Gl": "glutenhaltiges Getreide und daraus hergestellte Erzeugnisse (z. B. Weizen, Roggen, Gerste etc.)",
      "Sl": "Sellerie und Sellerieerzeugnisse",
      "Sw": "Schwefeldioxid und Sulfite (Konzentration über 10mg/kg oder 10mg/l)"
    },
    "PriceAttendant": 3.5,
    "PriceGuest": 4.7,
    "PriceStudent": 2.2,
    "LactoseFree": true,
    "Vegan": true
  },
  {
    "Name": "#curryWURSTtag..., Geflügelbratwurst (La,Sl), Grillsoße (2,9,Sl,Sf), Pommes Frites (Sf)",
    "Category": "CampusKlassiker",
    "Date": "2021-11-25T00:00:00Z",
    "Additives": {
      "2": "Konservierungsstoff",
      "9": "Süßungsmittel",
      "La": "Milch und Milcherzeugnisse (einschl. Laktose)",
      "Sf": "Senf und Senferzeugnisse",
      "Sl": "Sellerie und Sellerieerzeugnisse"
    },
    "PriceAttendant": 4.7,
    "PriceGuest": 5.9,
    "PriceStudent": 3.4,
    "Beef": true,
    "Poultry": true
  },
  {
    "Name": "#curryWURSTtag..., vegetarische Currywurst (2,9,Ei,Sl,Sf), Grillsoße (2,9,Sl,Sf), Pommes Frites (Sf)",
    "Category": "CampusKlassiker",
    "Date": "2021-11-25T00:00:00Z",
    "Additives": {
      "2": "Konservierungsstoff",
      "9": "Süßungsmittel",
      "Ei": "Ei und Eierzeugnisse",
      "Sf": "Senf und Senferzeugnisse",
      "Sl": "Sellerie und Sellerieerzeugnisse"
    },
    "PriceAttendant": 4.7,
    "PriceGuest": 5.9,
    "PriceStudent": 3.4,
    "LactoseFree": true,
    "Vegetarian": true
  },
  {
    "Name": "#curryWURSTtag..., Currybratwurst (3,4,8,Sf), Grillsoße (2,9,Sl,Sf), Pommes Frites (Sf)",
    "Category": "CampusKlassiker",
    "Date": "2021-11-25T00:00:00Z",
    "Additives": {
      "2": "Konservierungsstoff",
      "3": "Antioxidationsmittel",
      "4": "Geschmacksverstärker",
      "8": "Phosphat",
      "9": "Süßungsmittel",
      "Sf": "Senf und Senferzeugnisse",
      "Sl": "Sellerie und Sellerieerzeugnisse"
    },
    "PriceAttendant": 4.7,
    "PriceGuest": 5.9,
    "PriceStudent": 3.4,
    "LactoseFree": true,
    "Pig": true
  }
]
