[
	{
		"Additives": {
			"3": "Antioxidationsmittel",
			"Ei": "Ei/-erzeugnisse",
			"Gl": "Glutenhaltiges Getreide und daraus hergestellte Erzeugnissse",
			"La": "Milch/-erzeugnisse (einschl. Laktose)"
		},
		"Beef": false,
		"Category": "Aus dem Suppentopf und Süßes",
		"Date": "2019-07-26T00:00:00.000Z",
		"Fish": false,
		"LactoseFree": false,
		"Name": "2 Quarkkeulchen (Gl, Ei, La), Apfelmus (3)",
		"Pig": false,
		"Poultry": false,
		"PriceAttendant": 2.6,
		"PriceGuest": 3.25,
		"PriceStudent": 1.4,
		"Vegan": false,
		"Vegetarian": true
	},
	{
		"Additives": {
			"Ei": "Ei/-erzeugnisse",
			"Gl": "Glutenhaltiges Getreide und daraus hergestellte Erzeugnissse",
			"La": "Milch/-erzeugnisse (einschl. Laktose)",
			"So": "Soja/-erzeugnisse"
		},
		"Beef": false,
		"Category": "Beliebt und gerne gegessen",
		"Date": "2019-07-26T00:00:00.000Z",
		"Fish": false,
		"LactoseFree": false,
		"Name": "Hähnchenbrust im Kokosmantel (Gl, Ei, So), Karotten (La), Basmatireis, Currydip (La)",
		"Pig": false,
		"Poultry": true,
		"PriceAttendant": 4.1,
		"PriceGuest": 5.15,
		"PriceStudent": 2.8,
		"Vegan": false,
		"Vegetarian": false
	},
	{
		"Additives": {
			"8": "Phosphat",
			"La": "Milch/-erzeugnisse (einschl. Laktose)",
			"Sf": "Senf/-erzeugnisse",
			"Sl": "Sellerie/-erzeugnisse"
		},
		"Beef": false,
		"Category": "Beliebt und gerne gegessen",
		"Date": "2019-07-26T00:00:00.000Z",
		"Fish": false,
		"LactoseFree": false,
		"Name": "Thüringer Bratwurst (8, Sl, Sf), Zwiebelsoße (Sl), Erbsen-Karotten Gemüse (La), Kartoffelpüree (La)",
		"Pig": true,
		"Poultry": false,
		"PriceAttendant": 4.1,
		"PriceGuest": 5.15,
		"PriceStudent": 2.8,
		"Vegan": false,
		"Vegetarian": false
	},
	{
		"Additives": {
			"La": "Milch/-erzeugnisse (einschl. Laktose)"
		},
		"Beef": false,
		"Category": "Gemüse-Bar pro 100g",
		"Date": "2019-07-26T00:00:00.000Z",
		"Fish": false,
		"LactoseFree": false,
		"Name": "Prinzessbohnen, Karotten (La), gebratene Zucchini, Tellerrösti",
		"Pig": false,
		"Poultry": false,
		"PriceAttendant": 0.8,
		"PriceGuest": 1,
		"PriceStudent": 0.6,
		"Vegan": false,
		"Vegetarian": true
	},
	{
		"Additives": {
			"Gl": "Glutenhaltiges Getreide und daraus hergestellte Erzeugnissse"
		},
		"Beef": false,
		"Category": "Pasta-Bar pro 100g",
		"Date": "2019-07-26T00:00:00.000Z",
		"Fish": false,
		"LactoseFree": true,
		"Name": "Pasta mit Tofu und Spinat (Gl)",
		"Pig": false,
		"Poultry": false,
		"PriceAttendant": 0.8,
		"PriceGuest": 1,
		"PriceStudent": 0.6,
		"Vegan": true,
		"Vegetarian": false
	},
	{
		"Additives": {
			"Ei": "Ei/-erzeugnisse",
			"Gl": "Glutenhaltiges Getreide und daraus hergestellte Erzeugnissse"
		},
		"Beef": false,
		"Category": "Vegetarisch",
		"Date": "2019-07-26T00:00:00.000Z",
		"Fish": false,
		"LactoseFree": true,
		"Name": "Gnocchi a la Romana mit Gemüse in Tomatensoße (Gl, Ei)",
		"Pig": false,
		"Poultry": false,
		"PriceAttendant": 4.6,
		"PriceGuest": 5.75,
		"PriceStudent": 3.3,
		"Vegan": false,
		"Vegetarian": true
	}
]
